{
    "file_name": "/app/content/003b9182-453b-43e9-a3e0-fe8af940780c_2021-10-29T23-07-33-093Z.pdf",
    "resume_content": "Oleksandr Kryvonosov\nPalm Harbor, FL\nokrishka@gmail.com\n7273868416\nSkills: Java 8, C/C++, C#, SQL, PL/SQL, XSLT, Oracle, Servlets, JSP, Spring Framework, Web services,\nKafka, Gemfire, Hazelcast, Redis, Apache Flink, JUnit, Mockito, Linux/Unix shell scripts, design patterns\nAuthorized to work in the US for any employer\nWork Experience\nJava Developer eTrading\nCitibank - Tampa, FL\nJuly 2018 to Present\nWorking as an independent contractor in Citi Credit eTrading platform. Developing multithreaded high-\nthroughput microservices applications using Java 8, Spring Integration, LMAX Disruptor, Gemfire,\nHazelcast, Redis, Kafka, TIBCO EMS, Apache Flink, Docker\nSoftware Developer\nSCC SoftComputer - Clearwater, FL\nNovember 2008 to July 2018\nWorking as programmer in Healthcare domain. Developing information systems for laboratories and\nblood banks. \nResponsibilities: \n* Experience working as part of a large multi-region team \n* Participated in Design, Development and support phases of Software Development Life Cycle (SDLC).\n* Experience in building SOAP and RESTful web services \n* Used and implemented the application using Spring modules and Hibernate. \n* Used Spring Core for dependency injection/Inversion of Control (IoC). \n* Implemented spring configuration files for the beans defined and properties to be injected into them\nusing Spring Dependency Injection. \n* Proficient in writing SQL queries, PL/SQL, functions and Stored Procedures. \n* Worked with Oracle RDBMS, including but not limited to data export-import \n* Worked on Java Multithreading and Collections. \n* Experience with Hadoop, Apache Spark \n* Hands on Docker \n* C/C++ \n* Experience in development of application components using technologies such as JSP, Servlets,\nExpression Language, jQuery, JavaScript, Json. \n* Utilized AJAX to increase web page interactivity, speed and functionality. \n* Used Eclipse as an IDE for code development. \n* Used XSLT to create XML transformations \n* Utilized Junit, Spring Test DbUnit, Mockito, Java Reflection API for unit testing \n* Used various Java, J2EE design patterns like singleton, builder, strategy etc. \n* Used ANT and Maven for project build. \n* C# Windows Forms Application using Visual Studio \n* Used Log4j and Logback for logging \n* Experience in Shell scripting to perform debugging tasks on Unix environment \n* Experience in Perl scripting to perform various tasks on Unix environment \n* Used SVN, Bitbucket for version control\nSoftware Programmer\nInformational system development - Dnipro\nMarch 2003 to November 2008\nResponsibilities: \n- Coding (C/C++, PL/SQL, XSLT) \n- Analyzing, debugging, fixing coding problems \n- Troubleshooting support issues \n- Designing new software components\nEducation\nMaster's in Computer Science\nNational Mining University - Dnipro\nSeptember 1996 to June 2001\nSkills\nSpring (3 years), Java (7 years), C# (2 years), Perl (3 years), C (10+ years), JPA (3 years), C++ (1 year),\nPL/SQL (6 years), Hibernate (1 year), Rest\n",
    "personal_information": {
        "emails": "okrishka@gmail.com",
        "contact_number": {
            "primary": "7273868416",
            "alternate": null
        },
        "profiles_urls": {
            "linkedin": null,
            "github": null
        },
        "Location": {
            "addressLine": "Palm Harbor FL /\"United States/\"",
            "addressKeywords": null,
            "city": "Palm Harbor",
            "state": "Florida",
            "stateCode": "FL",
            "country": "United States",
            "countryCode": "US",
            "continent": "North America",
            "continentCode": "NA",
            "zipCode": "None",
            "lat": 28.0994672,
            "lon": -82.6934407,
            "point": "28.0994672,-82.6934407",
            "area": "None"
        },
        "name": "Oleksandr Kryvonosov"
    },
    "education": [
        {
            "college": "national mining university",
            "description": "responsibilities: - coding (c/c++, pl/sql, xslt) - analyzing, debugging, fixing coding problems - troubleshooting support issues - designing new software components education master's in computer science national mining university - dnipro september 1996 to june 2001",
            "startDate": "1996",
            "endDate": "2001",
            "location": "",
            "degree": "computer science",
            "department": "computers & mathematics",
            "isCurrentEd": false
        }
    ],
    "skills": [
        "unix shell scripts",
        "restful web services",
        "j2ee design patterns",
        "pl sql",
        "spring framework",
        "web services",
        "apache flink",
        "unix shell",
        "shell scripts",
        "design patterns",
        "java developer",
        "spring integration",
        "tibco ems",
        "docker software",
        "software developer",
        "information systems",
        "software development",
        "spring core",
        "dependency injection",
        "sql queries",
        "oracle rdbms",
        "java multithreading",
        "apache spark",
        "unit testing",
        "windows forms",
        "visual studio",
        "shell scripting",
        "perl scripting",
        "version control",
        "system development",
        "computer science",
        "skills",
        "java",
        "sql",
        "pl",
        "xslt",
        "oracle",
        "servlets",
        "jsp",
        "spring",
        "framework",
        "web",
        "services",
        "kafka",
        "gemfire",
        "hazelcast",
        "redis",
        "apache",
        "flink",
        "junit",
        "mockito",
        "linux",
        "unix",
        "shell",
        "scripts",
        "design",
        "experience",
        "developer",
        "credit",
        "microservices",
        "applications",
        "integration",
        "tibco",
        "ems",
        "docker",
        "software",
        "healthcare",
        "information",
        "systems",
        "team",
        "development",
        "support",
        "building",
        "soap",
        "restful",
        "application",
        "core",
        "control",
        "configuration",
        "writing",
        "rdbms",
        "data",
        "export",
        "import",
        "multithreading",
        "hadoop",
        "spark",
        "components",
        "jquery",
        "javascript",
        "ajax",
        "eclipse",
        "ide",
        "code",
        "xml",
        "transformations",
        "test",
        "api",
        "testing",
        "j2ee",
        "strategy",
        "ant",
        "maven",
        "project",
        "windows",
        "forms",
        "studio",
        "log4j",
        "logging",
        "scripting",
        "debugging",
        "environment",
        "perl",
        "svn",
        "bitbucket",
        "version",
        "system",
        "march",
        "coding",
        "troubleshooting",
        "designing",
        "education",
        "computer",
        "science",
        "mining",
        "jpa",
        "hibernate",
        "software development life cycle",
        "sdlc",
        "inversion of control",
        "ioc",
        "collections",
        "json",
        "c++",
        "c#",
        "healthcare domain",
        "them",
        "stored procedures",
        "functionality"
    ],
    "experience": [
        {
            "company_name": " ",
            "content": "July 2018 to Present\nWorking as an independent contractor in Citi Credit eTrading platform. Developing multithreaded high - \nthroughput microservices applications using Java 8, Spring Integration, LMAX Disruptor, Gemfire,\nHazelcast, Redis, Kafka, TIBCO EMS, Apache Flink, Docker\nSoftware Developer\nSCC SoftComputer - Clearwater, FL",
            "date": "July 2018 to Present",
            "end_date": [
                2021,
                10,
                29
            ],
            "industry": "Data Processing & Outsourced Services",
            "is_current_exp": true,
            "job_title": [
                "independent contractor"
            ],
            "number_of_days": 1216,
            "skills": [
                "spring integration",
                "tibco ems",
                "apache flink",
                "docker software",
                "software developer",
                "credit",
                "microservices",
                "applications",
                "java",
                "spring",
                "integration",
                "gemfire",
                "hazelcast",
                "redis",
                "kafka",
                "tibco",
                "ems",
                "apache",
                "flink",
                "docker",
                "software",
                "developer"
            ],
            "start_date": [
                2018,
                7,
                1
            ]
        },
        {
            "company_name": " ",
            "content": "November 2008 to July 2018\nWorking as programmer in Healthcare domain. Developing information systems for laboratories and\nblood banks. \nResponsibilities: \n* Experience working as part of a large multi - region team \n* Participated in Design, Development and support phases of Software Development Life Cycle (SDLC).\n* Experience in building SOAP and RESTful web services \n* Used and implemented the application using Spring modules and Hibernate. \n* Used Spring Core for dependency injection/Inversion of Control (IoC). \n* Implemented spring configuration files for the beans defined and properties to be injected into them\nusing Spring Dependency Injection. \n* Proficient in writing SQL queries, PL/SQL, functions and Stored Procedures. \n* Worked with Oracle RDBMS, including but not limited to data export - import \n* Worked on Java Multithreading and Collections. \n* Experience with Hadoop, Apache Spark \n* Hands on Docker \n* C/C++ \n* Experience in development of application components using technologies such as JSP, Servlets,\nExpression Language, jQuery, JavaScript, Json. \n* Utilized AJAX to increase web page interactivity, speed and functionality. \n* Used Eclipse as an IDE for code development. \n* Used XSLT to create XML transformations \n* Utilized Junit, Spring Test DbUnit, Mockito, Java Reflection API for unit testing \n* Used various Java, J2EE design patterns like singleton, builder, strategy etc. \n* Used ANT and Maven for project build. \n* C# Windows Forms Application using Visual Studio \n* Used Log4j and Logback for logging \n* Experience in Shell scripting to perform debugging tasks on Unix environment \n* Experience in Perl scripting to perform various tasks on Unix environment \n* Used SVN, Bitbucket for version control\nSoftware Programmer\nInformational system development - Dnipro",
            "date": "November 2008 to July 2018",
            "end_date": [
                2018,
                7,
                1
            ],
            "industry": "Health Care Technology",
            "is_current_exp": false,
            "job_title": [
                "software developer"
            ],
            "number_of_days": 3529,
            "skills": [
                "restful web services",
                "j2ee design patterns",
                "information systems",
                "software development",
                "web services",
                "spring core",
                "dependency injection",
                "sql queries",
                "pl sql",
                "oracle rdbms",
                "java multithreading",
                "apache spark",
                "unit testing",
                "design patterns",
                "windows forms",
                "visual studio",
                "shell scripting",
                "perl scripting",
                "version control",
                "system development",
                "healthcare",
                "information",
                "systems",
                "experience",
                "team",
                "design",
                "development",
                "support",
                "software",
                "building",
                "soap",
                "restful",
                "web",
                "services",
                "application",
                "spring",
                "core",
                "control",
                "configuration",
                "writing",
                "sql",
                "pl",
                "oracle",
                "rdbms",
                "data",
                "export",
                "import",
                "java",
                "multithreading",
                "hadoop",
                "apache",
                "spark",
                "docker",
                "components",
                "jsp",
                "servlets",
                "jquery",
                "javascript",
                "ajax",
                "eclipse",
                "ide",
                "code",
                "xslt",
                "xml",
                "transformations",
                "junit",
                "test",
                "mockito",
                "api",
                "testing",
                "j2ee",
                "strategy",
                "ant",
                "maven",
                "project",
                "windows",
                "forms",
                "studio",
                "log4j",
                "logging",
                "shell",
                "scripting",
                "debugging",
                "unix",
                "environment",
                "perl",
                "svn",
                "bitbucket",
                "version",
                "system",
                "software development life cycle",
                "sdlc",
                "hibernate",
                "inversion of control",
                "ioc",
                "collections",
                "json",
                "healthcare domain",
                "them",
                "stored procedures",
                "functionality"
            ],
            "start_date": [
                2008,
                11,
                1
            ]
        },
        {
            "company_name": " ",
            "content": "March 2003 to November 2008\nResponsibilities: \n - Coding (C/C++, PL/SQL, XSLT) \n - Analyzing, debugging, fixing coding problems \n - Troubleshooting support issues \n - Designing new software components\nEducation\nMaster's in Computer Science\nNational Mining University - Dnipro",
            "date": "March 2003 to November 2008",
            "end_date": [
                2008,
                11,
                1
            ],
            "industry": "IT Consulting & Other Services",
            "is_current_exp": false,
            "job_title": [
                " "
            ],
            "number_of_days": 2072,
            "skills": [
                "pl sql",
                "computer science",
                "march",
                "coding",
                "pl",
                "sql",
                "xslt",
                "debugging",
                "troubleshooting",
                "support",
                "designing",
                "software",
                "components",
                "education",
                "computer",
                "science",
                "mining"
            ],
            "start_date": [
                2003,
                3,
                1
            ]
        }
    ],
    "gap_years_info": {
        "workExp": [],
        "afterEdu": [
            {
                "periodStart": {
                    "year": 2002,
                    "month": 0,
                    "day": 0
                },
                "periodEnd": {
                    "year": 0,
                    "month": 0,
                    "day": 0
                }
            }
        ]
    },
    "certification": [
        "java developer",
        "java 8",
        "sql pl sql"
    ],
    "job_tenure_insights": {
        "total_experience_in_years": 19,
        "total_experience_in_days": 6935,
        "total_job_switches": 2,
        "average_months_at_a_job": 115.58,
        "average_years_at_a_job": 9,
        "average_days_at_a_job": 3467
    }
}